{
  "id": "guides/custom-ui",
  "title": "Custom UI",
  "description": "Tùy biến giao diện VortexStream theo thiết kế của bạn.",
  "source": "@site/docs/guides/custom-ui.md",
  "sourceDirName": "guides",
  "slug": "/guides/custom-ui",
  "permalink": "/docs/guides/custom-ui",
  "draft": false,
  "unlisted": false,
  "editUrl": "https://github.com/vortexstream/vortexstream/tree/main/apps/docs/docs/guides/custom-ui.md",
  "tags": [],
  "version": "current",
  "lastUpdatedBy": "locT-581",
  "lastUpdatedAt": 1766514744000,
  "sidebarPosition": 3,
  "frontMatter": {
    "sidebar_position": 3
  },
  "sidebar": "tutorialSidebar",
  "previous": {
    "title": "Next.js Integration",
    "permalink": "/docs/guides/nextjs-integration"
  },
  "next": {
    "title": "Gestures",
    "permalink": "/docs/guides/gestures"
  }
}